{
  "FormKey": "013810:Skyrim.esm",
  "EditorID": "WinterholdCollegeArcanaeum",
  "Name": {
    "TargetLanguage": "English",
    "Value": "The Arcanaeum"
  },
  "Flags": [
    "IsInteriorCell",
    "PublicArea"
  ],
  "Lighting": {
    "AmbientColor": "#003C3C3C",
    "DirectionalColor": "#00000000",
    "FogNearColor": "#00000000",
    "FogNear": 500.0,
    "FogFar": 10000.0,
    "FogPower": 1.0,
    "AmbientColors": {
      "DirectionalXPlus": "#00553C1C",
      "DirectionalXMinus": "#00553C1C",
      "DirectionalYPlus": "#00553C1C",
      "DirectionalYMinus": "#00553C1C",
      "DirectionalZPlus": "#00553C1C",
      "DirectionalZMinus": "#00553C1C",
      "Specular": "#00000000",
      "Scale": 1.0
    },
    "FogFarColor": "#00000000",
    "FogMax": 0.9,
    "LightFadeBegin": 31000.0,
    "LightFadeEnd": 41000.0,
    "Inherits": [
      "AmbientColor",
      "FogColor",
      "FogNear",
      "FogFar",
      "FogPower",
      "FogMax",
      "LightFadeDistances"
    ]
  },
  "LightingTemplate": "0A1196:Skyrim.esm",
  "WaterHeight": -2.1474836E+09,
  "Location": "01EB79:Skyrim.esm",
  "Owner": "01C193:Skyrim.esm",
  "AcousticSpace": "0FF495:Skyrim.esm",
  "Music": "01BA72:Skyrim.esm",
  "ImageSpace": "059B60:Skyrim.esm"
}