{
  "FormKey": "0237D2:Skyrim.esm",
  "IsCompressed": true,
  "MajorRecordFlagsRaw": 262144,
  "EditorID": "BlackreachWeatherTest2",
  "SkyrimMajorRecordFlags": [
    "Compressed"
  ],
  "Flags": [
    "HasWater"
  ],
  "Grid": {
    "Point": "3, 3",
    "Flags": "2014261248"
  },
  "WaterHeight": 3.4028235E+38,
  "Regions": [
    "048C2E:Skyrim.esm"
  ],
  "TemporaryUnknownGroupData": 1,
  "Temporary": [
    {
      "MutagenObjectType": "PlacedObject",
      "FormKey": "04E7FD:Skyrim.esm",
      "MajorRecordFlagsRaw": 196608,
      "SkyrimMajorRecordFlags": [
        "0x10000",
        "Dangerous_OffLimits_InteriorCell"
      ],
      "Base": "0879AC:Skyrim.esm",
      "Radius": 406.5561,
      "LightData": {
        "FadeOffset": 3.2359052,
        "ShadowDepthBias": 49.5
      },
      "LocationReference": "018EE8:Skyrim.esm",
      "Placement": {
        "Position": "15388.699, 13458.451, 1494.261",
        "Rotation": "0, 0, 3.633191"
      }
    },
    {
      "MutagenObjectType": "PlacedObject",
      "FormKey": "0CE0CA:Skyrim.esm",
      "MajorRecordFlagsRaw": 65536,
      "SkyrimMajorRecordFlags": [
        "0x10000"
      ],
      "Base": "0B9E2A:Skyrim.esm",
      "Radius": 803.2545,
      "LightData": {
        "FadeOffset": 0.46963155,
        "ShadowDepthBias": 1.0
      },
      "LocationReference": "018EE8:Skyrim.esm",
      "Placement": {
        "Position": "14593.586, 12645.399, 1618.8508"
      }
    },
    {
      "MutagenObjectType": "PlacedObject",
      "FormKey": "0D8F2E:Skyrim.esm",
      "MajorRecordFlagsRaw": 196608,
      "SkyrimMajorRecordFlags": [
        "0x10000",
        "Dangerous_OffLimits_InteriorCell"
      ],
      "Base": "0B9E2A:Skyrim.esm",
      "Radius": 523.79675,
      "LightData": {
        "FadeOffset": 2.2666335,
        "ShadowDepthBias": 1.0
      },
      "LocationReference": "018EE8:Skyrim.esm",
      "Placement": {
        "Position": "12321.252, 16302.139, 1215.8337"
      }
    },
    {
      "MutagenObjectType": "PlacedObject",
      "FormKey": "0D8F26:Skyrim.esm",
      "MajorRecordFlagsRaw": 65536,
      "SkyrimMajorRecordFlags": [
        "0x10000"
      ],
      "Base": "0B9E2A:Skyrim.esm",
      "Radius": 671.59143,
      "LightData": {
        "FadeOffset": 2.2666335,
        "ShadowDepthBias": 1.0
      },
      "LocationReference": "018EE8:Skyrim.esm",
      "Placement": {
        "Position": "12533.534, 12908.512, 1458.9326"
      }
    }
  ],
  "MajorFlags": [
    "0x40000"
  ]
}